PyRKHSstats/__init__.py
PyRKHSstats/combinatorics_utilities.py
PyRKHSstats/conditional_independence_testing.py
PyRKHSstats/dHSIC.py
PyRKHSstats/data_handling.py
PyRKHSstats/fscic.py
PyRKHSstats/fsic.py
PyRKHSstats/hscic.py
PyRKHSstats/hscic_checks.py
PyRKHSstats/hscic_numpy_vs_pytorch.py
PyRKHSstats/hscic_pytorch.py
PyRKHSstats/hscic_pytorch_checks.py
PyRKHSstats/hsic.py
PyRKHSstats/hsic_checks.py
PyRKHSstats/kcit.py
PyRKHSstats/kcit_checks.py
PyRKHSstats/kernel_wrapper.py
PyRKHSstats/mmd.py
PyRKHSstats/mmd_checks.py
PyRKHSstats/mmd_jmlr_paper_replication.py
PyRKHSstats/nfsic_checks.py
PyRKHSstats/temp_speed_check.py
PyRKHSstats/two_sample_testing.py
PyRKHSstats/utilities.py
PyRKHSstats/test/__init__.py
PyRKHSstats/test/test_combinatorics_utilities.py
PyRKHSstats/test/test_data_handling.py
PyRKHSstats/test/test_hsic.py
PyRKHSstats/test/test_kernel_wrapper.py
PyRKHSstats-2.1.0.dist-info/LICENSE
PyRKHSstats-2.1.0.dist-info/METADATA
PyRKHSstats-2.1.0.dist-info/WHEEL
PyRKHSstats-2.1.0.dist-info/top_level.txt
PyRKHSstats-2.1.0.dist-info/RECORD
