Metadata-Version: 2.1
Name: PyRKHSstats
Version: 2.1.0
Summary: A Python package for kernel methods in Statistics/ML.
Home-page: https://github.com/Black-Swan-ICL/PyRKHSstats
Author: K. M-H
Author-email: kmh.pro@protonmail.com
License: GNU General Public License v3.0
Platform: UNKNOWN
Classifier: License :: OSI Approved :: GNU General Public License v3 (GPLv3)
Classifier: Programming Language :: Python :: 3
Classifier: Programming Language :: Python :: 3.8
Classifier: Topic :: Scientific/Engineering
Classifier: Topic :: Scientific/Engineering :: Information Analysis
Classifier: Intended Audience :: Science/Research
Classifier: Intended Audience :: Financial and Insurance Industry
Requires-Python: >=3.8
Requires-Dist: numpy
Requires-Dist: scipy
Requires-Dist: pandas
Requires-Dist: scikit-learn
Requires-Dist: GPy
Requires-Dist: pyyaml
